django_scoped_idx/__init__.py
django_scoped_idx/fields.py
django_scoped_idx-0.1.1.dist-info/METADATA
django_scoped_idx-0.1.1.dist-info/WHEEL
django_scoped_idx-0.1.1.dist-info/RECORD
