Metadata-Version: 2.1
Name: django-scoped-idx
Version: 0.1.1
Summary: 
Author: Anjal Bam
Author-email: anjalbam81@gmail.com
Requires-Python: >=3.10,<4.0
Classifier: Programming Language :: Python :: 3
Classifier: Programming Language :: Python :: 3.10
Classifier: Programming Language :: Python :: 3.11
Requires-Dist: django (>=4.2.1,<5.0.0)
Requires-Dist: shortuuid (>=1.0.11,<2.0.0)
Requires-Dist: six (>=1.16.0,<2.0.0)
